{
    "stateList": [
        {
            "state": {
                "h": 0.0,
                "s": 1.0,
                "b": 1.0
            },
            "smooth": true,
            "waitTime": 0,
            "transitionTime": 10
        },
        {
            "state": {
                "h": 1.0,
                "s": 1.0,
                "b": 1.0
            },
            "smooth": true,
            "waitTime": 0,
            "transitionTime": 0
        }
    ],
    "loop": true
}